DoesIsLibrary/__init__.py
DoesIsLibrary/kwgenerator.py
robotframework_doesislibrary-0.1.0.dist-info/LICENSE.txt
robotframework_doesislibrary-0.1.0.dist-info/METADATA
robotframework_doesislibrary-0.1.0.dist-info/WHEEL
robotframework_doesislibrary-0.1.0.dist-info/top_level.txt
robotframework_doesislibrary-0.1.0.dist-info/RECORD
