Metadata-Version: 2.1
Name: robotframework-doesislibrary
Version: 0.1.0
Summary: Robot Framework Does Is Library
Home-page: https://github.com/sebastianciupinski/robotframework-doesislibrary
Author: Sebastian Ciupinski
Author-email: sebastian.ciupinski+robotframework-doesis@gmail.com
License: UNKNOWN
Platform: UNKNOWN
Classifier: Programming Language :: Python
Classifier: License :: OSI Approved :: MIT License
Classifier: Operating System :: OS Independent
